{
  "videos": [
    {
      "id": 1,
      "title": "Dagakara Hedakari (දඟකාරි හැඩකාරි) Live Cover",
      "videoId": "jIgCoIQ-r30",
      "description": "\nVocals - Shihan Mihiranga With Sirasa Super Stars , BnS , Ashanthi De Alwis , 6th Lane, Centigradz , Randhir Witana, Iraj Weeraratne , Romesh & Lakshan\nLyrics - Upul Shantha Sannasgala\nMusic - Ranga Dasanayake"
    },
    {
      "id": 2,
      "title": "Dan Sapada - Wasthi x Prizma Live",
      "videoId": "jJ0DOS3GiwE",
      "description": "Live Mix  by Inoch Jonathan (PRIZMA)\nPost Audio Mixed & Mastered by Sadeep Sasanka (PRIZMA)"
    },
    {
      "id": 3,
      "title": "Prizma Weddings - Sanasennam Ma (සැනසෙන්නම් මා ) Live Cover",
      "videoId": "VdjJKLVgnNg",
      "description": "Lights - Wathila Manakamal (Hilight Events)\nLive Track Mixed & Mastered by Inoch Jonathan\nVideography & Edit - Sadeep Sasanka"
    },
    {
      "id": 4,
      "title": "Hithumathe (හිතුමතේ) Live Cover by Prizma",
      "videoId": "NDqt6HNbEcA",
      "description": "Prizma Weddings - Hithumathe (හිතුමතේ)  Live Cover by Prizma"
    },
    {
      "id": 5,
      "title": "Jaya Sri Medley by Prizma : Sheela / Piyamanne / Adara Lowe ‪@Jayasri‬",
      "videoId": "tc5jx5g4wTY",
      "description": "Feel the rhythm! 🌞🎶 We bring you a Reggae Medley packed with pure island vibes. Kick back, turn it up, and let the good times roll! 🌴🔥 "
    },
    {
      "id": 6,
      "title": "Dátha Dara | Supun Perera Live Cover With Prizma",
      "videoId": "GsjS5ptWX1c",
      "description": "Artist - Ridma Weerawardane, Danith Sri, Methun SK, Supun Perera, Dinesh Gamage, Dinupa Kodagoda "
    }
  ]
}